pypkgs_cz/__init__.py
pypkgs_cz/pypkgs_cz.py
pypkgs_cz-0.1.0.dist-info/LICENSE
pypkgs_cz-0.1.0.dist-info/WHEEL
pypkgs_cz-0.1.0.dist-info/METADATA
pypkgs_cz-0.1.0.dist-info/RECORD
